MANIFEST.in
README.rst
setup.cfg
setup.py
docs/HISTORY.txt
docs/INSTALL.txt
docs/LICENSE.GPL
docs/LICENSE.txt
src/mls/__init__.py
src/mls.apiclient.egg-info/PKG-INFO
src/mls.apiclient.egg-info/SOURCES.txt
src/mls.apiclient.egg-info/dependency_links.txt
src/mls.apiclient.egg-info/namespace_packages.txt
src/mls.apiclient.egg-info/not-zip-safe
src/mls.apiclient.egg-info/requires.txt
src/mls.apiclient.egg-info/top_level.txt
src/mls/apiclient/__init__.py
src/mls/apiclient/api.py
src/mls/apiclient/client.py
src/mls/apiclient/exceptions.py
src/mls/apiclient/resources.py
src/mls/apiclient/testing.py
src/mls/apiclient/utils.py
src/mls/apiclient/tests/__init__.py
src/mls/apiclient/tests/base.py
src/mls/apiclient/tests/test_api.py
src/mls/apiclient/tests/test_exceptions.py
src/mls/apiclient/tests/test_integration.py
src/mls/apiclient/tests/test_listing_categories.py
src/mls/apiclient/tests/test_resources.py
src/mls/apiclient/tests/test_utils.py
src/mls/apiclient/tests/utils.py
src/mls/apiclient/tests/fixtures/basic_single.json
src/mls/apiclient/tests/fixtures/category_listing_types_en.json
src/mls/apiclient/tests/fixtures/category_view_types_en.json
src/mls/apiclient/tests/fixtures/development_en.json
src/mls/apiclient/tests/fixtures/development_fields_en.json
src/mls/apiclient/tests/fixtures/development_fields_order.json
src/mls/apiclient/tests/fixtures/development_list_0.json
src/mls/apiclient/tests/fixtures/development_list_1.json
src/mls/apiclient/tests/fixtures/group_fields_en.json
src/mls/apiclient/tests/fixtures/group_fields_order.json
src/mls/apiclient/tests/fixtures/group_list_en.json
src/mls/apiclient/tests/fixtures/listing_residential_lease_en.json
src/mls/apiclient/tests/fixtures/phase_fields_en.json
src/mls/apiclient/tests/fixtures/phase_fields_order.json
src/mls/apiclient/tests/fixtures/phase_list_en.json
src/mls/apiclient/tests/fixtures/integration/development_list_11-agency2.json
src/mls/apiclient/tests/fixtures/integration/development_list_15-agency1.json
src/mls/apiclient/tests/fixtures/integration/development_list_26-1.json
src/mls/apiclient/tests/fixtures/integration/development_list_26-2.json