Metadata-Version: 1.1
Name: mls.apiclient
Version: 1.4
Summary: Python client for the RESTful API of the Propertyshelf MLS.
Home-page: https://github.com/propertyshelf/mls.apiclient
Author: Propertyshelf, Inc.
Author-email: development@propertyshelf.com
License: GPL
Download-URL: http://pypi.python.org/pypi/mls.apiclient
Keywords: MLS API client
Platform: UNKNOWN
Classifier: Development Status :: 4 - Beta
Classifier: Environment :: Web Environment
Classifier: Intended Audience :: Other Audience
Classifier: License :: OSI Approved :: GNU General Public License (GPL)
Classifier: Natural Language :: English
Classifier: Operating System :: OS Independent
Classifier: Programming Language :: Python
